{
    "finger_flexion": {
        "right_hand": {
            "thumb_finger": "straight",
            "index_finger": "straight",
            "middle_finger": "straight",
            "ring_finger": "straight",
            "little_finger": "straight"
        },
        "left_hand": {
            "thumb_finger": "straight",
            "index_finger": "bent",
            "middle_finger": "bent",
            "ring_finger": "bent",
            "little_finger": "bent"
        }
    },
    "finger_proximity": {
        "right_hand": {
            "index-middle_fingers": "close",
            "middle-ring_fingers,": "close",
            "ring-little_fingers": "close"
        },
        "left_hand": {
            "index-middle_fingers": "close",
            "middle-ring_fingers,": "close",
            "ring-little_fingers": "close"
        }
    },
    "finger_thumb_contact": {
        "right_hand": {
            "thumb-index_fingers": "contact",
            "thumb-middle_fingers": "contact",
            "thumb-ring_fingers": "contact",
            "thumb-little_fingers": "non-contact"
        },
        "left_hand": {
            "thumb-index_fingers": "contact",
            "thumb-middle_fingers": "contact",
            "thumb-ring_fingers": "contact",
            "thumb-little_fingers": "contact"
        }
    },
    "thumb_direction": {
        "right_hand": "down",
        "left_hand": "right"
    },
    "palm_orientation": {
        "right_hand": "inward",
        "left_hand": "inward"
    },
    "hand_landmarks": {
        "right_hand": [
            [
                0.5453003644943237,
                0.5640436410903931,
                -2.4926924879764556e-07
            ],
            [
                0.5257697701454163,
                0.546100914478302,
                0.00566473975777626
            ],
            [
                0.5010055899620056,
                0.545204758644104,
                0.005866846069693565
            ],
            [
                0.48278242349624634,
                0.5611742734909058,
                0.003706958144903183
            ],
            [
                0.4730652868747711,
                0.5828201770782471,
                0.0008994917152449489
            ],
            [
                0.48983585834503174,
                0.5240381956100464,
                0.003587657818570733
            ],
            [
                0.4623185694217682,
                0.5591356754302979,
                -0.004616387188434601
            ],
            [
                0.45745447278022766,
                0.5906543731689453,
                -0.011439397931098938
            ],
            [
                0.461637407541275,
                0.6116211414337158,
                -0.01468602940440178
            ],
            [
                0.4878300726413727,
                0.532712996006012,
                -0.001733856275677681
            ],
            [
                0.46223920583724976,
                0.5706844329833984,
                -0.006811284460127354
            ],
            [
                0.4600750505924225,
                0.6003168225288391,
                -0.010414978489279747
            ],
            [
                0.46445977687835693,
                0.6216096878051758,
                -0.012841761112213135
            ],
            [
                0.48878014087677,
                0.5472834706306458,
                -0.007209113333374262
            ],
            [
                0.46500903367996216,
                0.5838432908058167,
                -0.010461976751685143
            ],
            [
                0.4636271595954895,
                0.6115802526473999,
                -0.011115600354969501
            ],
            [
                0.4669731855392456,
                0.6298984885215759,
                -0.01176813431084156
            ],
            [
                0.49192172288894653,
                0.5662065744400024,
                -0.012235305272042751
            ],
            [
                0.4739188551902771,
                0.5947786569595337,
                -0.013898089528083801
            ],
            [
                0.47037431597709656,
                0.6157519221305847,
                -0.012706042267382145
            ],
            [
                0.4705888628959656,
                0.6317975521087646,
                -0.011594066396355629
            ]
        ],
        "left_hand": [
            [
                0.519358217716217,
                0.8246799111366272,
                7.164469906228987e-08
            ],
            [
                0.5312636494636536,
                0.7867529988288879,
                -0.012094121426343918
            ],
            [
                0.5540093183517456,
                0.7783968448638916,
                -0.01903011091053486
            ],
            [
                0.5773718953132629,
                0.7919294834136963,
                -0.023456145077943802
            ],
            [
                0.5939582586288452,
                0.8032708764076233,
                -0.027315208688378334
            ],
            [
                0.5659071207046509,
                0.8180943727493286,
                -0.022128643468022346
            ],
            [
                0.5984448194503784,
                0.8265995383262634,
                -0.03216563165187836
            ],
            [
                0.6168531179428101,
                0.816331148147583,
                -0.03777815029025078
            ],
            [
                0.62763512134552,
                0.8009616732597351,
                -0.040262773633003235
            ],
            [
                0.5668699145317078,
                0.8384843468666077,
                -0.019083930179476738
            ],
            [
                0.5985007286071777,
                0.8385797739028931,
                -0.027343137189745903
            ],
            [
                0.6173228621482849,
                0.8240374326705933,
                -0.030754635110497475
            ],
            [
                0.628928005695343,
                0.8069099187850952,
                -0.032564207911491394
            ],
            [
                0.5668672323226929,
                0.8516924977302551,
                -0.016389809548854828
            ],
            [
                0.5958884954452515,
                0.8483214974403381,
                -0.023441562429070473
            ],
            [
                0.6129847168922424,
                0.8329487442970276,
                -0.024447578936815262
            ],
            [
                0.623726487159729,
                0.8167040348052979,
                -0.02424415573477745
            ],
            [
                0.566781759262085,
                0.8575875163078308,
                -0.014387776143848896
            ],
            [
                0.5900753736495972,
                0.8546351194381714,
                -0.02002290077507496
            ],
            [
                0.6036380529403687,
                0.8431984186172485,
                -0.020383531227707863
            ],
            [
                0.6122024655342102,
                0.82917720079422,
                -0.019540978595614433
            ]
        ]
    }
}