{
    "finger_flexion": {
        "right_hand": {
            "thumb_finger": "bent",
            "index_finger": "straight",
            "middle_finger": "straight",
            "ring_finger": "straight",
            "little_finger": "straight"
        }
    },
    "finger_proximity": {
        "right_hand": {
            "index-middle_fingers": "apart",
            "middle-ring_fingers,": "apart",
            "ring-little_fingers": "apart"
        }
    },
    "finger_thumb_contact": {
        "right_hand": {
            "thumb-index_fingers": "non-contact",
            "thumb-middle_fingers": "non-contact",
            "thumb-ring_fingers": "non-contact",
            "thumb-little_fingers": "non-contact"
        }
    },
    "thumb_direction": {
        "right_hand": "up"
    },
    "palm_orientation": {
        "right_hand": "outward"
    },
    "hand_landmarks": {
        "right_hand": [
            [
                0.6547108888626099,
                0.7402694225311279,
                1.4126318603757682e-07
            ],
            [
                0.6351761221885681,
                0.7135298848152161,
                -0.007654576096683741
            ],
            [
                0.6221150159835815,
                0.6761083006858826,
                -0.013133569620549679
            ],
            [
                0.6110126972198486,
                0.6482114195823669,
                -0.018493397161364555
            ],
            [
                0.5982739329338074,
                0.63051438331604,
                -0.024422280490398407
            ],
            [
                0.6426191926002502,
                0.6108527183532715,
                -0.00830401573330164
            ],
            [
                0.6345292925834656,
                0.5622851848602295,
                -0.0158047117292881
            ],
            [
                0.6304769515991211,
                0.5326017141342163,
                -0.022599559277296066
            ],
            [
                0.6271824836730957,
                0.5071495771408081,
                -0.027927227318286896
            ],
            [
                0.660865306854248,
                0.6077056527137756,
                -0.011699683964252472
            ],
            [
                0.6635337471961975,
                0.5502469539642334,
                -0.01867472380399704
            ],
            [
                0.6647670269012451,
                0.5139318108558655,
                -0.025999100878834724
            ],
            [
                0.6648427844047546,
                0.48448604345321655,
                -0.03147762641310692
            ],
            [
                0.676253080368042,
                0.619821310043335,
                -0.01611575298011303
            ],
            [
                0.6899081468582153,
                0.5716168880462646,
                -0.02480475977063179
            ],
            [
                0.6979427337646484,
                0.5395378470420837,
                -0.031767863780260086
            ],
            [
                0.7034856677055359,
                0.5125054121017456,
                -0.036500100046396255
            ],
            [
                0.6881451606750488,
                0.643130898475647,
                -0.020948776975274086
            ],
            [
                0.7034401297569275,
                0.6114941835403442,
                -0.028827674686908722
            ],
            [
                0.7128496766090393,
                0.5909461975097656,
                -0.03181127831339836
            ],
            [
                0.7202438116073608,
                0.5728676915168762,
                -0.03370291367173195
            ]
        ]
    }
}