{
    "finger_flexion": {
        "right_hand": {
            "thumb_finger": "straight",
            "index_finger": "straight",
            "middle_finger": "straight",
            "ring_finger": "straight",
            "little_finger": "straight"
        }
    },
    "finger_proximity": {
        "right_hand": {
            "index-middle_fingers": "close",
            "middle-ring_fingers,": "apart",
            "ring-little_fingers": "apart"
        }
    },
    "finger_thumb_contact": {
        "right_hand": {
            "thumb-index_fingers": "non-contact",
            "thumb-middle_fingers": "non-contact",
            "thumb-ring_fingers": "non-contact",
            "thumb-little_fingers": "non-contact"
        }
    },
    "thumb_direction": {
        "right_hand": "up"
    },
    "palm_orientation": {
        "right_hand": "outward"
    },
    "hand_landmarks": {
        "right_hand": [
            [
                0.6186236143112183,
                0.8821269273757935,
                9.808139367351032e-08
            ],
            [
                0.5863183736801147,
                0.8617121577262878,
                -0.011852973140776157
            ],
            [
                0.5616984963417053,
                0.8184742331504822,
                -0.01914159022271633
            ],
            [
                0.5513230562210083,
                0.7732393145561218,
                -0.025484150275588036
            ],
            [
                0.5434475541114807,
                0.7317818403244019,
                -0.03191157430410385
            ],
            [
                0.5827566385269165,
                0.77094566822052,
                -0.018857762217521667
            ],
            [
                0.5776206254959106,
                0.721660852432251,
                -0.03164970129728317
            ],
            [
                0.5772963762283325,
                0.6951758861541748,
                -0.04066998139023781
            ],
            [
                0.5777177214622498,
                0.669803261756897,
                -0.04772746562957764
            ],
            [
                0.6058906316757202,
                0.7687538266181946,
                -0.022600216791033745
            ],
            [
                0.6016392111778259,
                0.720633327960968,
                -0.035721778869628906
            ],
            [
                0.5998015999794006,
                0.6914175748825073,
                -0.04494265466928482
            ],
            [
                0.5974140763282776,
                0.6630200743675232,
                -0.05194598808884621
            ],
            [
                0.627994179725647,
                0.7817187309265137,
                -0.02761678211390972
            ],
            [
                0.6292739510536194,
                0.7364158630371094,
                -0.04366283118724823
            ],
            [
                0.6300955414772034,
                0.7086359858512878,
                -0.050616949796676636
            ],
            [
                0.6280161142349243,
                0.679510772228241,
                -0.05491282790899277
            ],
            [
                0.6489936113357544,
                0.8043428063392639,
                -0.03309601917862892
            ],
            [
                0.6554208993911743,
                0.7690858840942383,
                -0.04908609390258789
            ],
            [
                0.6581501960754395,
                0.7463034391403198,
                -0.05445704236626625
            ],
            [
                0.6578687429428101,
                0.7219251394271851,
                -0.05746251344680786
            ]
        ]
    }
}