{
    "finger_flexion": {
        "right_hand": {
            "thumb_finger": "straight",
            "index_finger": "bent",
            "middle_finger": "bent",
            "ring_finger": "bent",
            "little_finger": "straight"
        }
    },
    "finger_proximity": {
        "right_hand": {
            "index-middle_fingers": "apart",
            "middle-ring_fingers,": "apart",
            "ring-little_fingers": "apart"
        }
    },
    "finger_thumb_contact": {
        "right_hand": {
            "thumb-index_fingers": "non-contact",
            "thumb-middle_fingers": "contact",
            "thumb-ring_fingers": "non-contact",
            "thumb-little_fingers": "non-contact"
        }
    },
    "thumb_direction": {
        "right_hand": "up"
    },
    "palm_orientation": {
        "right_hand": "outward"
    },
    "hand_landmarks": {
        "right_hand": [
            [
                0.7557672262191772,
                0.8952367305755615,
                -2.0205317241561715e-07
            ],
            [
                0.7162748575210571,
                0.8731217384338379,
                -0.009470147080719471
            ],
            [
                0.6834516525268555,
                0.8215548992156982,
                -0.016385678201913834
            ],
            [
                0.6679807305335999,
                0.7729372978210449,
                -0.02511291578412056
            ],
            [
                0.660243809223175,
                0.7286705374717712,
                -0.03263692557811737
            ],
            [
                0.6909535527229309,
                0.7339142560958862,
                -0.002980545861646533
            ],
            [
                0.6787625551223755,
                0.6621478199958801,
                -0.02095697447657585
            ],
            [
                0.6695771217346191,
                0.6524755954742432,
                -0.03319837898015976
            ],
            [
                0.6651495099067688,
                0.6577547788619995,
                -0.039035286754369736
            ],
            [
                0.7118774056434631,
                0.7275006771087646,
                -0.007457793224602938
            ],
            [
                0.6974213123321533,
                0.6546541452407837,
                -0.029048068448901176
            ],
            [
                0.6913735270500183,
                0.6735381484031677,
                -0.039549048990011215
            ],
            [
                0.6901206374168396,
                0.6965779662132263,
                -0.04162619262933731
            ],
            [
                0.7337870597839355,
                0.727904200553894,
                -0.014297853223979473
            ],
            [
                0.7213515639305115,
                0.662528395652771,
                -0.03323734551668167
            ],
            [
                0.7148669958114624,
                0.6888392567634583,
                -0.033580537885427475
            ],
            [
                0.7123878598213196,
                0.7162514925003052,
                -0.028411278501152992
            ],
            [
                0.7577632665634155,
                0.7355315089225769,
                -0.022191530093550682
            ],
            [
                0.7457037568092346,
                0.6781816482543945,
                -0.033437181264162064
            ],
            [
                0.7354955673217773,
                0.6567206382751465,
                -0.032769981771707535
            ],
            [
                0.727220356464386,
                0.6394156217575073,
                -0.029111236333847046
            ]
        ]
    }
}