{
    "finger_flexion": {
        "right_hand": {
            "thumb_finger": "straight",
            "index_finger": "straight",
            "middle_finger": "straight",
            "ring_finger": "straight",
            "little_finger": "straight"
        }
    },
    "finger_proximity": {
        "right_hand": {
            "index-middle_fingers": "close",
            "middle-ring_fingers,": "close",
            "ring-little_fingers": "apart"
        }
    },
    "finger_thumb_contact": {
        "right_hand": {
            "thumb-index_fingers": "non-contact",
            "thumb-middle_fingers": "non-contact",
            "thumb-ring_fingers": "non-contact",
            "thumb-little_fingers": "non-contact"
        }
    },
    "thumb_direction": {
        "right_hand": "left"
    },
    "palm_orientation": {
        "right_hand": "outward"
    },
    "hand_landmarks": {
        "right_hand": [
            [
                0.6094001531600952,
                0.5718663334846497,
                8.094999515151358e-08
            ],
            [
                0.577302098274231,
                0.5839851498603821,
                -0.005862785503268242
            ],
            [
                0.5471667647361755,
                0.5733211636543274,
                -0.0062001473270356655
            ],
            [
                0.5264102220535278,
                0.5641253590583801,
                -0.007135631516575813
            ],
            [
                0.5122209191322327,
                0.5640501976013184,
                -0.007906831800937653
            ],
            [
                0.5506606698036194,
                0.4963076412677765,
                0.0071436879225075245
            ],
            [
                0.5350316166877747,
                0.45696452260017395,
                0.0053620366379618645
            ],
            [
                0.5264764428138733,
                0.43359851837158203,
                0.0012180095072835684
            ],
            [
                0.5187984704971313,
                0.41448527574539185,
                -0.002344295149669051
            ],
            [
                0.5632771849632263,
                0.47599831223487854,
                0.005144091323018074
            ],
            [
                0.5455721020698547,
                0.4320838451385498,
                0.004443432670086622
            ],
            [
                0.5336318016052246,
                0.4047471880912781,
                0.0004821691836696118
            ],
            [
                0.523261547088623,
                0.3835787773132324,
                -0.0028891165275126696
            ],
            [
                0.5779519081115723,
                0.4630034267902374,
                0.0010012600105255842
            ],
            [
                0.5623315572738647,
                0.4232034683227539,
                -0.001482154126279056
            ],
            [
                0.550865888595581,
                0.40232548117637634,
                -0.0056024231016635895
            ],
            [
                0.5400400757789612,
                0.3856145143508911,
                -0.008550611324608326
            ],
            [
                0.5957401990890503,
                0.45495039224624634,
                -0.0042841555550694466
            ],
            [
                0.5845926403999329,
                0.4199116826057434,
                -0.0068985652178525925
            ],
            [
                0.5750448703765869,
                0.40188413858413696,
                -0.00840984471142292
            ],
            [
                0.5652851462364197,
                0.3868575096130371,
                -0.009611418470740318
            ]
        ]
    }
}