{
    "finger_flexion": {
        "right_hand": {
            "thumb_finger": "straight",
            "index_finger": "straight",
            "middle_finger": "bent",
            "ring_finger": "bent",
            "little_finger": "bent"
        }
    },
    "finger_proximity": {
        "right_hand": {
            "index-middle_fingers": "apart",
            "middle-ring_fingers,": "apart",
            "ring-little_fingers": "apart"
        }
    },
    "finger_thumb_contact": {
        "right_hand": {
            "thumb-index_fingers": "non-contact",
            "thumb-middle_fingers": "non-contact",
            "thumb-ring_fingers": "non-contact",
            "thumb-little_fingers": "non-contact"
        }
    },
    "thumb_direction": {
        "right_hand": "left"
    },
    "palm_orientation": {
        "right_hand": "left"
    },
    "hand_landmarks": {
        "right_hand": [
            [
                0.5977706909179688,
                0.8207400441169739,
                2.447097102731277e-08
            ],
            [
                0.5771369338035583,
                0.8022592663764954,
                -0.00547192245721817
            ],
            [
                0.549663782119751,
                0.7966153621673584,
                -0.011682667769491673
            ],
            [
                0.5259788036346436,
                0.8012593388557434,
                -0.0153438039124012
            ],
            [
                0.5084851384162903,
                0.797076940536499,
                -0.019631439819931984
            ],
            [
                0.5589805841445923,
                0.7760003805160522,
                -0.03107290342450142
            ],
            [
                0.5295278429985046,
                0.7980782389640808,
                -0.04129667207598686
            ],
            [
                0.5146399140357971,
                0.8277155160903931,
                -0.043997228145599365
            ],
            [
                0.5053384304046631,
                0.8527482748031616,
                -0.044870659708976746
            ],
            [
                0.5722507238388062,
                0.8021491169929504,
                -0.03191833943128586
            ],
            [
                0.5346928834915161,
                0.8558799028396606,
                -0.04408051446080208
            ],
            [
                0.5401376485824585,
                0.8622908592224121,
                -0.042147450149059296
            ],
            [
                0.5521750450134277,
                0.8528546094894409,
                -0.038688287138938904
            ],
            [
                0.5834676623344421,
                0.8318500518798828,
                -0.03126629814505577
            ],
            [
                0.5477015376091003,
                0.87996506690979,
                -0.040900252759456635
            ],
            [
                0.5534906983375549,
                0.88028883934021,
                -0.033073753118515015
            ],
            [
                0.564452052116394,
                0.8669038414955139,
                -0.02533671446144581
            ],
            [
                0.5929399728775024,
                0.861997127532959,
                -0.030437417328357697
            ],
            [
                0.5619927644729614,
                0.8996539115905762,
                -0.03628457710146904
            ],
            [
                0.5648387670516968,
                0.8963181376457214,
                -0.029935458675026894
            ],
            [
                0.574499785900116,
                0.8811386227607727,
                -0.023914773017168045
            ]
        ]
    }
}