{
    "finger_flexion": {
        "right_hand": {
            "thumb_finger": "bent",
            "index_finger": "straight",
            "middle_finger": "straight",
            "ring_finger": "straight",
            "little_finger": "bent"
        }
    },
    "finger_proximity": {
        "right_hand": {
            "index-middle_fingers": "close",
            "middle-ring_fingers,": "close",
            "ring-little_fingers": "apart"
        }
    },
    "finger_thumb_contact": {
        "right_hand": {
            "thumb-index_fingers": "non-contact",
            "thumb-middle_fingers": "non-contact",
            "thumb-ring_fingers": "non-contact",
            "thumb-little_fingers": "contact"
        }
    },
    "thumb_direction": {
        "right_hand": "up"
    },
    "palm_orientation": {
        "right_hand": "outward"
    },
    "hand_landmarks": {
        "right_hand": [
            [
                0.609936535358429,
                0.4468352794647217,
                7.726831086074526e-08
            ],
            [
                0.5924497246742249,
                0.4422813653945923,
                -0.007155333645641804
            ],
            [
                0.5755408406257629,
                0.41544803977012634,
                -0.009210120886564255
            ],
            [
                0.5653819441795349,
                0.39008280634880066,
                -0.010748562403023243
            ],
            [
                0.5539776682853699,
                0.3731546998023987,
                -0.012212364003062248
            ],
            [
                0.5748324990272522,
                0.37293368577957153,
                -0.003438287414610386
            ],
            [
                0.5679885745048523,
                0.34131577610969543,
                -0.008448945358395576
            ],
            [
                0.5657293200492859,
                0.32106515765190125,
                -0.01285611279308796
            ],
            [
                0.5635894536972046,
                0.3034857511520386,
                -0.01620749570429325
            ],
            [
                0.5863572359085083,
                0.3657595217227936,
                -0.004676795098930597
            ],
            [
                0.5799669623374939,
                0.33032259345054626,
                -0.00815332867205143
            ],
            [
                0.5765438675880432,
                0.30798637866973877,
                -0.012234975583851337
            ],
            [
                0.5733194351196289,
                0.29006415605545044,
                -0.015456640161573887
            ],
            [
                0.5984470844268799,
                0.3684028685092926,
                -0.007175263483077288
            ],
            [
                0.5946081876754761,
                0.33742555975914,
                -0.013114328496158123
            ],
            [
                0.5897060036659241,
                0.3250378966331482,
                -0.01723427325487137
            ],
            [
                0.584627628326416,
                0.31564000248908997,
                -0.02008466050028801
            ],
            [
                0.6114967465400696,
                0.37724724411964417,
                -0.01023778598755598
            ],
            [
                0.6087077856063843,
                0.36418280005455017,
                -0.017031120136380196
            ],
            [
                0.6054913997650146,
                0.3693532347679138,
                -0.019010575488209724
            ],
            [
                0.602044939994812,
                0.3761603534221649,
                -0.02004307694733143
            ]
        ]
    }
}