{
    "finger_flexion": {
        "right_hand": {
            "thumb_finger": "straight",
            "index_finger": "straight",
            "middle_finger": "straight",
            "ring_finger": "straight",
            "little_finger": "straight"
        },
        "left_hand": {
            "thumb_finger": "bent",
            "index_finger": "straight",
            "middle_finger": "straight",
            "ring_finger": "straight",
            "little_finger": "straight"
        }
    },
    "finger_proximity": {
        "right_hand": {
            "index-middle_fingers": "close",
            "middle-ring_fingers,": "close",
            "ring-little_fingers": "apart"
        },
        "left_hand": {
            "index-middle_fingers": "close",
            "middle-ring_fingers,": "close",
            "ring-little_fingers": "apart"
        }
    },
    "finger_thumb_contact": {
        "right_hand": {
            "thumb-index_fingers": "non-contact",
            "thumb-middle_fingers": "non-contact",
            "thumb-ring_fingers": "non-contact",
            "thumb-little_fingers": "non-contact"
        },
        "left_hand": {
            "thumb-index_fingers": "non-contact",
            "thumb-middle_fingers": "non-contact",
            "thumb-ring_fingers": "non-contact",
            "thumb-little_fingers": "non-contact"
        }
    },
    "thumb_direction": {
        "right_hand": "up",
        "left_hand": "up"
    },
    "palm_orientation": {
        "right_hand": "outward",
        "left_hand": "outward"
    },
    "hand_landmarks": {
        "right_hand": [
            [
                0.6598158478736877,
                0.6797249913215637,
                1.5426788024797133e-07
            ],
            [
                0.6400411128997803,
                0.6297205090522766,
                -0.009694571606814861
            ],
            [
                0.6395472288131714,
                0.5687088370323181,
                -0.013160660862922668
            ],
            [
                0.647832989692688,
                0.5229690670967102,
                -0.016403967514634132
            ],
            [
                0.6519864797592163,
                0.4851781129837036,
                -0.019356543198227882
            ],
            [
                0.6813468337059021,
                0.5269811153411865,
                -0.003183359280228615
            ],
            [
                0.6965175271034241,
                0.472469300031662,
                -0.011753943748772144
            ],
            [
                0.7078002691268921,
                0.4394896328449249,
                -0.020073167979717255
            ],
            [
                0.7180585861206055,
                0.4129815101623535,
                -0.025960251688957214
            ],
            [
                0.6983435750007629,
                0.5361576080322266,
                -0.005628073588013649
            ],
            [
                0.7162649631500244,
                0.47226017713546753,
                -0.011889372020959854
            ],
            [
                0.728891134262085,
                0.4336695075035095,
                -0.01890871487557888
            ],
            [
                0.7401295900344849,
                0.4031052589416504,
                -0.024133095517754555
            ],
            [
                0.7108981609344482,
                0.5558675527572632,
                -0.010085382498800755
            ],
            [
                0.7307215332984924,
                0.49785181879997253,
                -0.017407873645424843
            ],
            [
                0.7426769733428955,
                0.4637508690357208,
                -0.022160202264785767
            ],
            [
                0.752648115158081,
                0.43493416905403137,
                -0.025481712073087692
            ],
            [
                0.7209693789482117,
                0.587018609046936,
                -0.0158147681504488
            ],
            [
                0.7409087419509888,
                0.5509904623031616,
                -0.02233060821890831
            ],
            [
                0.7530943751335144,
                0.5263490080833435,
                -0.024227207526564598
            ],
            [
                0.7629982829093933,
                0.5037652254104614,
                -0.025268258526921272
            ]
        ],
        "left_hand": [
            [
                0.32343921065330505,
                0.7196881771087646,
                8.968481779447757e-08
            ],
            [
                0.34244510531425476,
                0.661946177482605,
                -0.008475424721837044
            ],
            [
                0.3377930521965027,
                0.597406268119812,
                -0.008697103708982468
            ],
            [
                0.3246622383594513,
                0.5509610176086426,
                -0.009100750088691711
            ],
            [
                0.31624719500541687,
                0.5160490870475769,
                -0.009063869714736938
            ],
            [
                0.3005202114582062,
                0.551803708076477,
                0.00100116734392941
            ],
            [
                0.28528523445129395,
                0.4957830309867859,
                -0.004720168653875589
            ],
            [
                0.2741660177707672,
                0.46502721309661865,
                -0.01104210689663887
            ],
            [
                0.26275330781936646,
                0.4416150748729706,
                -0.01575460471212864
            ],
            [
                0.28227707743644714,
                0.5627477765083313,
                -0.0003706531133502722
            ],
            [
                0.2643292248249054,
                0.4988410770893097,
                -0.004510723520070314
            ],
            [
                0.25205326080322266,
                0.46179723739624023,
                -0.009861269034445286
            ],
            [
                0.24096783995628357,
                0.43453431129455566,
                -0.013948936015367508
            ],
            [
                0.2680008113384247,
                0.5835491418838501,
                -0.0037441730964928865
            ],
            [
                0.24943682551383972,
                0.524466335773468,
                -0.008417187258601189
            ],
            [
                0.23818126320838928,
                0.49017253518104553,
                -0.012790167704224586
            ],
            [
                0.2287396788597107,
                0.4624840021133423,
                -0.015981025993824005
            ],
            [
                0.2559013366699219,
                0.6156668066978455,
                -0.008375710807740688
            ],
            [
                0.23736485838890076,
                0.5751985311508179,
                -0.013382305391132832
            ],
            [
                0.22585317492485046,
                0.5487698316574097,
                -0.015599967911839485
            ],
            [
                0.2162053883075714,
                0.5254606604576111,
                -0.016938993707299232
            ]
        ]
    }
}