{
    "finger_flexion": {
        "right_hand": {
            "thumb_finger": "bent",
            "index_finger": "straight",
            "middle_finger": "straight",
            "ring_finger": "straight",
            "little_finger": "straight"
        }
    },
    "finger_proximity": {
        "right_hand": {
            "index-middle_fingers": "close",
            "middle-ring_fingers,": "close",
            "ring-little_fingers": "close"
        }
    },
    "finger_thumb_contact": {
        "right_hand": {
            "thumb-index_fingers": "non-contact",
            "thumb-middle_fingers": "non-contact",
            "thumb-ring_fingers": "non-contact",
            "thumb-little_fingers": "contact"
        }
    },
    "thumb_direction": {
        "right_hand": "up"
    },
    "palm_orientation": {
        "right_hand": "inward"
    },
    "hand_landmarks": {
        "right_hand": [
            [
                0.618826687335968,
                0.5514940619468689,
                -3.5245076190904e-08
            ],
            [
                0.6228450536727905,
                0.5244407653808594,
                0.001530989189632237
            ],
            [
                0.6231278777122498,
                0.4820522367954254,
                0.0018933335086330771
            ],
            [
                0.6185195446014404,
                0.4494600296020508,
                0.0016522707883268595
            ],
            [
                0.6123386025428772,
                0.4280344247817993,
                0.0009865635074675083
            ],
            [
                0.6326014995574951,
                0.4666335880756378,
                -0.0040426105260849
            ],
            [
                0.6205231547355652,
                0.4228655695915222,
                -0.009717506356537342
            ],
            [
                0.6104111075401306,
                0.3901737332344055,
                -0.013721405528485775
            ],
            [
                0.600422739982605,
                0.3653886914253235,
                -0.016437185928225517
            ],
            [
                0.6294803023338318,
                0.46580007672309875,
                -0.00809041503816843
            ],
            [
                0.6177757978439331,
                0.41730955243110657,
                -0.014007390476763248
            ],
            [
                0.6082270741462708,
                0.38289517164230347,
                -0.017756344750523567
            ],
            [
                0.5981563329696655,
                0.35501137375831604,
                -0.02025129459798336
            ],
            [
                0.6226938366889954,
                0.4678821861743927,
                -0.011913159862160683
            ],
            [
                0.6130366921424866,
                0.41968005895614624,
                -0.017250169068574905
            ],
            [
                0.6045889854431152,
                0.3875077962875366,
                -0.02038421668112278
            ],
            [
                0.5959622263908386,
                0.36233586072921753,
                -0.02209090255200863
            ],
            [
                0.6126241087913513,
                0.4725651741027832,
                -0.015512621961534023
            ],
            [
                0.60628342628479,
                0.4335286617279053,
                -0.02040301077067852
            ],
            [
                0.6006762981414795,
                0.40807414054870605,
                -0.02262822724878788
            ],
            [
                0.5946847200393677,
                0.3883998692035675,
                -0.023737501353025436
            ]
        ]
    }
}